usvseg/__init__.py
usvseg/func.py
usvseg/gui.py
usvseg/usvseg_prm.yaml
usvseg-1.0.2.dist-info/LICENSE.txt
usvseg-1.0.2.dist-info/METADATA
usvseg-1.0.2.dist-info/WHEEL
usvseg-1.0.2.dist-info/entry_points.txt
usvseg-1.0.2.dist-info/top_level.txt
usvseg-1.0.2.dist-info/RECORD
