Metadata-Version: 2.1
Name: usvseg
Version: 1.0.2
Summary: Python ver of USVSEG
Author-email: Jumpei Matsumoto <jm@med.u-toyama>
Project-URL: Homepage, https://github.com/MatsumotoJ/usvseg_python
Project-URL: Issues, https://github.com/MatsumotoJ/usvseg_python/issues
Classifier: Programming Language :: Python :: 3
Classifier: License :: OSI Approved :: MIT License
Classifier: Operating System :: OS Independent
Classifier: Intended Audience :: Science/Research
Classifier: Topic :: Scientific/Engineering
Requires-Python: >=3.6
License-File: LICENSE.txt
